<?xml version='1.0' encoding='utf-8'?>
<annotation><folder>polygonData</folder><filename>train33.png</filename><size><width>1024</width><height>768</height><depth>3</depth></size><object><name>circle</name><bndbox><points>[[117.71058315334774, 246.85097192224626], [129.80561555075593, 250.73866090712747]]</points><center>[117.71058315334774, 246.85097192224626]</center><R>12.704484811967795</R></bndbox></object><object><name>circle</name><bndbox><points>[[52.3, 14.9], [64.1, 18.2]]</points><center>[52.3, 14.9]</center><R>12.252754792290586</R></bndbox></object><object><name>circle</name><bndbox><points>[[25.9, 619.8], [34.1, 623.0]]</points><center>[25.9, 619.8]</center><R>8.802272433866174</R></bndbox></object><object><name>circle</name><bndbox><points>[[358.1, 685.0], [365.5, 687.7]]</points><center>[358.1, 685.0]</center><R>7.8771822373231855</R></bndbox></object><object><name>circle</name><bndbox><points>[[536.3, 677.8], [541.8, 679.6]]</points><center>[536.3, 677.8]</center><R>5.787054518492136</R></bndbox></object><object><name>circle</name><bndbox><points>[[614.6, 583.3], [621.0, 584.3]]</points><center>[614.6, 583.3]</center><R>6.4776538962806365</R></bndbox></object><object><name>circle</name><bndbox><points>[[905.2, 600.2], [913.9, 603.2]]</points><center>[905.2, 600.2]</center><R>9.202716990106715</R></bndbox></object><object><name>circle</name><bndbox><points>[[646.4, 369.8], [657.2, 371.2]]</points><center>[646.4, 369.8]</center><R>10.890362712049651</R></bndbox></object><object><name>circle</name><bndbox><points>[[704.2, 229.9], [710.5, 231.3]]</points><center>[704.2, 229.9]</center><R>6.453681120104978</R></bndbox></object><object><name>circle</name><bndbox><points>[[437.7, 425.9], [441.7, 427.1]]</points><center>[437.7, 425.9]</center><R>4.176122603564233</R></bndbox></object><object><name>circle</name><bndbox><points>[[906.3, 480.0], [915.6, 482.0]]</points><center>[906.3, 480.0]</center><R>9.512623192369247</R></bndbox></object><object><name>circle</name><bndbox><points>[[944.9, 200.5], [948.2, 201.4]]</points><center>[944.9, 200.5]</center><R>3.4205262752974814</R></bndbox></object><object><name>circle</name><bndbox><points>[[744.4, 276.2], [749.4, 276.9]]</points><center>[744.4, 276.2]</center><R>5.048762224545734</R></bndbox></object><object><name>circle</name><bndbox><points>[[151.9, 328.3], [156.1, 330.2]]</points><center>[151.9, 328.3]</center><R>4.609772228646424</R></bndbox></object><object><name>ellipse</name><bndbox><center>(609.0, 649.0)</center><points>[[606.0, 654.5], [605.4, 646.8], [612.4, 642.6], [613.4, 650.8]]</points><axis_func>(-1.8688117198323553, 0.5350993880571044, 1787.0294997714707, 322.7196842798857)</axis_func><fit_points>[[605.9489785754458, 654.6249469892327], [605.1933167718512, 646.5582577407527], [612.3238691066733, 642.7114768518265], [613.079530910268, 650.7781661003067]]</fit_points><axis>(6.755923326977578, 4.47213595499958)</axis><angle>-61.8</angle></bndbox></object><object><name>ellipse</name><bndbox><center>(366.0, 590.0)</center><points>[[366.6, 597.9], [374.0, 589.2], [365.1, 574.1], [357.1, 590.3]]</points><axis_func>(15.86665830734556, -0.06302524439050791, -5218.816939785011, 612.7877758546342)</axis_func><fit_points>[[365.3341529230885, 577.8152326491645], [357.63304086729016, 590.2478660518527], [366.8341537102342, 601.6152325995554], [374.5352657660325, 589.1825991968661]]</fit_points><axis>(11.923611030220645, 8.46788049041788)</axis><angle>86.4</angle></bndbox></object><object><name>ellipse</name><bndbox><center>(216.0, 402.0)</center><points>[[218.0, 408.2], [221.0, 400.1], [214.1, 393.8], [210.7, 403.2]]</points><axis_func>(3.557572029545901, -0.2810905517899474, -367.5935365738788, 462.3164832229663)</axis_func><fit_points>[[214.1791636657319, 394.3642653948627], [211.02015840278509, 403.00071045872534], [218.21623562358923, 408.7264396734001], [221.37524088653603, 400.08999460953737]]</fit_points><axis>(7.459390055493803, 5.378196723809943)</axis><angle>74.3</angle></bndbox></object><object><name>ellipse</name><bndbox><center>(647.0, 432.0)</center><points>[[641.5, 433.9], [645.4, 427.5], [652.4, 430.2], [648.1, 435.3]]</points><axis_func>(-0.3460607688285488, 2.8896658912974194, 655.9341622955784, -1437.4915879796645)</axis_func><fit_points>[[641.5334115692718, 433.9246166587144], [645.6226955032444, 428.14229386356055], [652.4113310893957, 430.1601954663252], [648.3220471554232, 435.9425182614791]]</fit_points><axis>(5.755432216610656, 4.127044947659294)</axis><angle>-19.1</angle></bndbox></object><object><name>ellipse</name><bndbox><center>(841.0, 705.0)</center><points>[[834.2, 704.7], [841.0, 699.7], [850.7, 705.4], [841.5, 710.6]]</points><axis_func>(-0.04587192195972366, 21.799827809222183, 743.588232841415, -17633.955145702468)</axis_func><fit_points>[[832.9943172448789, 705.3771825278646], [840.9930620963183, 699.5487967477711], [849.491810888826, 704.6204107868984], [841.4930660373865, 710.4487965669905]]</fit_points><axis>(8.25742090485885, 5.455730931781724)</axis><angle>-2.6</angle></bndbox></object><object><name>ellipse</name><bndbox><center>(940.0, 677.0)</center><points>[[939.6, 669.8], [932.8, 676.7], [939.5, 684.8], [945.9, 677.4]]</points><axis_func>(-149.9999983402484, 0.0066666719411192996, 141609.79844057772, 670.7970899893428)</axis_func><fit_points>[[939.5015948511535, 684.5607722439745], [932.9923961308464, 677.017044217906], [939.6015948522601, 669.5607722439745], [946.1107935725672, 677.1045002700431]]</fit_points><axis>(7.500166664814856, 6.559344479443058)</axis><angle>-89.6</angle></bndbox></object><object><name>ellipse</name><bndbox><center>(747.0, 290.0)</center><points>[[746.0, 281.0], [740.2, 290.6], [747.5, 305.9], [754.1, 290.2]]</points><axis_func>(16.60005447264448, -0.06024076617627449, -12102.640667493763, 335.3905537205729)</axis_func><fit_points>[[745.817277696647, 277.96676890999333], [739.6269797303555, 290.8348577769724], [747.3172727922341, 302.8667692054387], [753.5075707585256, 289.9986803384559]]</fit_points><axis>(12.472569903592431, 6.952877102322451)</axis><angle>86.6</angle></bndbox></object><object><name>circle</name><bndbox><points>[[971.1, 362.6], [973.9, 364.2]]</points><center>[971.1, 362.6]</center><R>3.2249030993193633</R></bndbox></object><object><name>ellipse</name><bndbox><center>(786.0, 127.0)</center><points>[[787.7, 123.4], [783.9, 125.8], [783.4, 130.5], [787.9, 128.2]]</points><axis_func>(-1.6529695032208338, 0.6049718388995314, 1425.4403216660987, -348.445981417895)</axis_func><fit_points>[[783.4727944703275, 130.3836858034431], [783.6254649723002, 125.6253571348978], [787.7693542900031, 123.28160345275523], [787.6166837880304, 128.03993212130052]]</fit_points><axis>(4.150301193889442, 2.332380757938118)</axis><angle>-58.8</angle></bndbox></object><object><name>ellipse</name><bndbox><center>(546.0, 186.0)</center><points>[[542.9, 177.3], [539.5, 187.9], [548.4, 194.0], [553.3, 183.0]]</points><axis_func>(3.0333909685164886, -0.3296640658861742, -1469.5197238538124, 365.59700515116236)</axis_func><fit_points>[[542.9171196289358, 177.3601634815875], [538.7156217636314, 188.0018229241653], [548.4219814160897, 194.05856150967156], [552.6234792813941, 183.41690206709404]]</fit_points><axis>(8.791188770581593, 7.3220557222681455)</axis><angle>71.8</angle></bndbox></object><object><name>circle</name><bndbox><points>[[79.2, 344.5], [81.9, 346.2]]</points><center>[79.2, 344.5]</center><R>3.19061122670876</R></bndbox></object><object><name>ellipse</name><bndbox><center>(541.0, 115.0)</center><points>[[547.4, 119.8], [543.3, 111.5], [533.9, 110.4], [538.3, 118.2]]</points><axis_func>(0.7063214006538828, -1.415786039108342, -266.7724240264707, 880.4938983820529)</axis_func><fit_points>[[533.907672866464, 110.33799129242527], [538.2143936148977, 118.49747385491867], [547.3442005420482, 119.8284983401685], [543.0374797936145, 111.6690157776751]]</fit_points><axis>(8.225113980973148, 4.180011961705374)</axis><angle>35.2</angle></bndbox></object><object><name>ellipse</name><bndbox><center>(60.0, 96.0)</center><points>[[57.0, 91.0], [57.9, 97.5], [64.6, 103.8], [63.0, 94.8]]</points><axis_func>(1.7086368615481138, -0.58526186718985, -6.469283351336928, 131.51241466971743)</axis_func><fit_points>[[56.39199769741523, 89.88416261080309], [57.66143328993423, 97.76537655760754], [63.91121908580157, 102.73178144514098], [62.64178349328257, 94.85056749833655]]</fit_points><axis>(7.443117626371355, 2.8853076092507033)</axis><angle>59.7</angle></bndbox></object><object><name>ellipse</name><bndbox><center>(214.0, 32.0)</center><points>[[203.5, 40.4], [208.5, 24.3], [228.3, 21.5], [219.8, 40.0]]</points><axis_func>(-0.7503089373498276, 1.3327843427262915, 192.96159592057631, -253.26225072443307)</axis_func><fit_points>[[201.74160913697256, 41.593063549770164], [208.4074797506868, 24.499975194328925], [226.68264906878932, 22.879578382129097], [220.01677845507507, 39.97266673757028]]</fit_points><axis>(15.590461827668868, 9.671866417605242)</axis><angle>-36.9</angle></bndbox></object></annotation>