<?xml version='1.0' encoding='utf-8'?>
<annotation><folder>polygonData</folder><filename>train61.png</filename><size><width>1024</width><height>768</height><depth>3</depth></size><object><name>circle</name><bndbox><points>[[138.8, 219.1], [146.2, 224.5]]</points><center>[138.8, 219.1]</center><R>9.160785992479015</R></bndbox></object><object><name>circle</name><bndbox><points>[[243.2, 265.1], [247.7, 267.3]]</points><center>[243.2, 265.1]</center><R>5.0089919145472726</R></bndbox></object><object><name>circle</name><bndbox><points>[[264.0, 305.7], [266.8, 306.7]]</points><center>[264.0, 305.7]</center><R>2.973213749463712</R></bndbox></object><object><name>ellipse</name><bndbox><center>(373.0, 362.0)</center><points>[[365.8, 356.7], [377.3, 357.2], [379.7, 368.5], [367.7, 368.1]]</points><axis_func>(0.8611369579502585, -1.16125546691292, 41.61263859072535, 795.2210760226616)</axis_func><fit_points>[[365.7239588909399, 356.5510559995947], [367.8931822355057, 368.00310691168943], [379.5403411203898, 368.44885336254123], [377.371117775824, 356.9968024504465]]</fit_points><axis>(9.116605728010832, 7.262403183519922)</axis><angle>40.7</angle></bndbox></object><object><name>circle</name><bndbox><points>[[329.4, 395.4], [326.3, 387.5]]</points><center>[329.4, 395.4]</center><R>8.486459803710817</R></bndbox></object><object><name>circle</name><bndbox><points>[[389.8, 583.3], [394.8, 586.8]]</points><center>[389.8, 583.3]</center><R>6.103277807866851</R></bndbox></object><object><name>circle</name><bndbox><points>[[222.0, 595.2], [226.3, 596.9]]</points><center>[222.0, 595.2]</center><R>4.623851208678743</R></bndbox></object><object><name>circle</name><bndbox><points>[[216.1, 695.6], [225.5, 698.0]]</points><center>[216.1, 695.6]</center><R>9.701546268507922</R></bndbox></object><object><name>ellipse</name><bndbox><center>(138.0, 260.0)</center><points>[[133.3, 264.4], [140.5, 261.6], [142.9, 255.3], [135.7, 257.3]]</points><axis_func>(-0.9783061444493637, 1.0221747667120828, 394.96067151990826, 118.26025505015889)</axis_func><fit_points>[[133.5892787895322, 264.2694592475499], [136.06363797633097, 257.3410724566123], [143.0446195155525, 255.0192413174219], [140.57026032875373, 261.9476281083595]]</fit_points><axis>(6.61381130665215, 3.2221886971436127)</axis><angle>-44.4</angle></bndbox></object><object><name>circle</name><bndbox><points>[[401.5, 325.4], [405.8, 327.1]]</points><center>[401.5, 325.4]</center><R>4.623851208678784</R></bndbox></object><object><name>circle</name><bndbox><points>[[500.6, 724.8], [507.4, 724.6]]</points><center>[500.6, 724.8]</center><R>6.802940540677932</R></bndbox></object><object><name>circle</name><bndbox><points>[[577.6, 559.1], [581.6, 562.0]]</points><center>[577.6, 559.1]</center><R>4.940647730814237</R></bndbox></object><object><name>circle</name><bndbox><points>[[520.9, 616.8], [523.2, 617.3]]</points><center>[520.9, 616.8]</center><R>2.3537204591880307</R></bndbox></object><object><name>circle</name><bndbox><points>[[562.9, 714.2], [565.1, 714.4]]</points><center>[562.9, 714.2]</center><R>2.209072203437491</R></bndbox></object><object><name>circle</name><bndbox><points>[[482.9, 676.6], [484.7, 676.9]]</points><center>[482.9, 676.6]</center><R>1.8248287590894696</R></bndbox></object><object><name>circle</name><bndbox><points>[[203.4, 157.0], [205.1, 157.0]]</points><center>[203.4, 157.0]</center><R>1.6999999999999886</R></bndbox></object><object><name>circle</name><bndbox><points>[[49.4, 692.2], [53.0, 693.0]]</points><center>[49.4, 692.2]</center><R>3.6878177829171466</R></bndbox></object><object><name>circle</name><bndbox><points>[[195.4, 749.5], [198.6, 750.1]]</points><center>[195.4, 749.5]</center><R>3.2557641192199345</R></bndbox></object><object><name>circle</name><bndbox><points>[[751.0, 402.8], [756.3, 403.6]]</points><center>[751.0, 402.8]</center><R>5.360037313302915</R></bndbox></object><object><name>circle</name><bndbox><points>[[727.8, 349.3], [731.3, 349.9]]</points><center>[727.8, 349.3]</center><R>3.551056180912935</R></bndbox></object><object><name>circle</name><bndbox><points>[[812.4, 557.1], [817.0, 559.7]]</points><center>[812.4, 557.1]</center><R>5.283937925449194</R></bndbox></object><object><name>circle</name><bndbox><points>[[963.0658436213992, 621.1913580246915], [966.4609053497942, 621.7057613168724]]</points><center>[963.0658436213992, 621.1913580246915]</center><R>3.433810549028487</R></bndbox></object><object><name>circle</name><bndbox><points>[[638.9, 213.7], [644.5, 217.9]]</points><center>[638.9, 213.7]</center><R>7.000000000000028</R></bndbox></object><object><name>circle</name><bndbox><points>[[631.1, 165.0], [634.9, 166.3]]</points><center>[631.1, 165.0]</center><R>4.016217125604601</R></bndbox></object><object><name>circle</name><bndbox><points>[[345.4, 52.5], [348.8, 54.7]]</points><center>[345.4, 52.5]</center><R>4.049691346263347</R></bndbox></object><object><name>circle</name><bndbox><points>[[897.165991902834, 11.732793522267214], [901.9230769230769, 15.072874493927133]]</points><center>[897.165991902834, 11.732793522267214]</center><R>5.812572475854758</R></bndbox></object><object><name>circle</name><bndbox><points>[[5.4, 390.0], [9.1, 388.5]]</points><center>[5.4, 390.0]</center><R>3.992492955535425</R></bndbox></object><object><name>ellipse</name><bndbox><center>(799.0, 246.0)</center><points>[[796.2, 250.6], [801.5, 247.8], [801.3, 242.5], [795.6, 244.8]]</points><axis_func>(-1.6989956080146649, 0.588582619530374, 1603.6305762320478, -223.73433865975502)</axis_func><fit_points>[[796.3931106323257, 250.56217901458922], [795.9686318071139, 244.75896371328386], [801.2483539420914, 242.31314195545474], [801.6728327673032, 248.1163572567598]]</fit_points><axis>(4.785916840063119, 3.309456148674572)</axis><angle>-59.5</angle></bndbox></object><object><name>ellipse</name><bndbox><center>(744.0, 29.0)</center><points>[[737.0, 22.9], [747.6, 26.0], [751.1, 35.5], [740.2, 32.6]]</points><axis_func>(0.9382478122262591, -1.0658164522010978, -668.9024402235123, 822.1836566333135)</axis_func><fit_points>[[737.1360524925944, 22.713848340765367], [740.63878163582, 32.79865802768029], [750.9261053173898, 35.65233523411416], [747.4233761741642, 25.56752554719924]]</fit_points><axis>(9.454760705591664, 4.957822102496208)</axis><angle>43.2</angle></bndbox></object><object><name>ellipse</name><bndbox><center>(7.0, 740.0)</center><points>[[14.0, 726.5], [13.7, 743.5], [0.7, 754.3], [0.8, 736.5]]</points><axis_func>(-2.0406450522016453, 0.49004112627016716, 755.3922304261785, 736.4593677840588)</axis_func><fit_points>[[0.7007302932908326, 753.9622886202467], [0.8915873354629467, 736.8962822460973], [14.261901425472974, 726.2887518472994], [14.071044383300862, 743.3547582214491]]</fit_points><axis>(15.408844862610543, 7.338426261808453)</axis><angle>-63.9</angle></bndbox></object></annotation>