<?xml version='1.0' encoding='utf-8'?>
<annotation><folder>polygonData</folder><filename>train164.png</filename><size><width>1024</width><height>768</height><depth>3</depth></size><object><name>circle</name><bndbox><points>[[195.55555555555554, 189.77777777777777], [200.0, 196.88888888888889]]</points><center>[195.55555555555554, 189.77777777777777]</center><R>8.385761006272546</R></bndbox></object><object><name>circle</name><bndbox><points>[[286.22222222222223, 104.88888888888889], [288.8888888888889, 108.0]]</points><center>[286.22222222222223, 104.88888888888889]</center><R>4.097575314352409</R></bndbox></object><object><name>circle</name><bndbox><points>[[465.77777777777777, 50.666666666666664], [468.8888888888889, 53.77777777777778]]</points><center>[465.77777777777777, 50.666666666666664]</center><R>4.399775527382987</R></bndbox></object><object><name>circle</name><bndbox><points>[[661.3333333333334, 78.22222222222223], [667.1111111111111, 84.44444444444444]]</points><center>[661.3333333333334, 78.22222222222223]</center><R>8.49109918868564</R></bndbox></object><object><name>circle</name><bndbox><points>[[414.6666666666667, 224.0], [417.77777777777777, 226.66666666666666]]</points><center>[414.6666666666667, 224.0]</center><R>4.097575314352369</R></bndbox></object><object><name>circle</name><bndbox><points>[[414.6666666666667, 339.1111111111111], [416.44444444444446, 344.0]]</points><center>[414.6666666666667, 339.1111111111111]</center><R>5.202088849208744</R></bndbox></object><object><name>circle</name><bndbox><points>[[192.0, 383.1111111111111], [193.33333333333334, 386.22222222222223]]</points><center>[192.0, 383.1111111111111]</center><R>3.384788047050659</R></bndbox></object><object><name>circle</name><bndbox><points>[[632.0, 365.77777777777777], [638.2222222222222, 376.44444444444446]]</points><center>[632.0, 365.77777777777777]</center><R>12.34883910173315</R></bndbox></object><object><name>circle</name><bndbox><points>[[611.5555555555555, 398.22222222222223], [613.3333333333334, 400.44444444444446]]</points><center>[611.5555555555555, 398.22222222222223]</center><R>2.845832994414636</R></bndbox></object><object><name>circle</name><bndbox><points>[[60.44444444444444, 437.3333333333333], [63.55555555555556, 446.6666666666667]]</points><center>[60.44444444444444, 437.3333333333333]</center><R>9.838197164968328</R></bndbox></object><object><name>circle</name><bndbox><points>[[74.22222222222223, 579.5555555555555], [76.44444444444444, 583.1111111111111]]</points><center>[74.22222222222223, 579.5555555555555]</center><R>4.192880503136253</R></bndbox></object><object><name>circle</name><bndbox><points>[[638.6666666666666, 596.4444444444445], [640.0, 600.8888888888889]]</points><center>[638.6666666666666, 596.4444444444445]</center><R>4.64013622618249</R></bndbox></object><object><name>circle</name><bndbox><points>[[713.7777777777778, 680.0], [714.6666666666666, 683.5555555555555]]</points><center>[713.7777777777778, 680.0]</center><R>3.6649827783267757</R></bndbox></object><object><name>circle</name><bndbox><points>[[465.3333333333333, 704.4444444444445], [468.0, 708.4444444444445]]</points><center>[465.3333333333333, 704.4444444444445]</center><R>4.807401700618663</R></bndbox></object><object><name>circle</name><bndbox><points>[[947.5555555555555, 584.4444444444445], [949.3333333333334, 588.4444444444445]]</points><center>[947.5555555555555, 584.4444444444445]</center><R>4.3772701341316225</R></bndbox></object><object><name>circle</name><bndbox><points>[[818.2222222222222, 452.0], [820.4444444444445, 457.3333333333333]]</points><center>[818.2222222222222, 452.0]</center><R>5.777777777777785</R></bndbox></object><object><name>circle</name><bndbox><points>[[975.5555555555555, 330.6666666666667], [976.8888888888889, 335.1111111111111]]</points><center>[975.5555555555555, 330.6666666666667]</center><R>4.6401362261824355</R></bndbox></object><object><name>ellipse</name><bndbox><center>(788.0, 50.0)</center><points>[[800.0, 60.0], [795.5555555555555, 42.666666666666664], [778.2222222222222, 41.333333333333336], [781.3333333333334, 56.44444444444444]]</points><axis_func>(0.9100873110542941, -1.0987956622175536, -667.4423973744233, 915.8564531729622)</axis_func><fit_points>[[777.5422738479826, 40.188959862928755], [781.4849191543368, 57.164213917741336], [798.7554713299583, 59.494821718163735], [794.8128260236041, 42.51956766335093]]</fit_points><axis>(14.3415136002334, 9.900741959975743)</axis><angle>42.3</angle></bndbox></object><object><name>ellipse</name><bndbox><center>(953.0, 216.0)</center><points>[[966.2222222222222, 208.0], [947.1111111111111, 209.33333333333334], [942.2222222222222, 223.55555555555554], [958.6666666666666, 222.22222222222223]]</points><axis_func>(-0.7089984436378555, 1.410440320447094, 892.268533429224, -1128.3597204348089)</axis_func><fit_points>[[941.7133281446822, 224.5952494216192], [948.3729077170568, 209.26366742897926], [965.0445250235102, 208.05346714632185], [958.3849454511356, 223.38504913896168]]</fit_points><axis>(14.30013381617437, 8.655263152955749)</axis><angle>-35.3</angle></bndbox></object><object><name>ellipse</name><bndbox><center>(343.0, 90.0)</center><points>[[330.6666666666667, 84.0], [346.6666666666667, 84.88888888888889], [352.44444444444446, 95.11111111111111], [340.0, 96.0]]</points><axis_func>(0.5288967240367876, -1.890728292525874, -91.12513444659676, 739.5926243647791)</axis_func><fit_points>[[332.5190618726024, 84.7431080576085], [340.2959366618932, 96.1854690865448], [354.1309381273977, 96.17355860905819], [346.35406333810687, 84.73119758012194]]</fit_points><axis>(12.224242257311168, 6.478835438717007)</axis><angle>27.9</angle></bndbox></object><object><name>ellipse</name><bndbox><center>(393.0, 278.0)</center><points>[[393.77777777777777, 268.44444444444446], [388.44444444444446, 277.3333333333333], [392.44444444444446, 284.44444444444446], [396.8888888888889, 278.22222222222223]]</points><axis_func>(-11.999807666163868, 0.08333466900638298, 4993.702191137668, 245.06227701673046)</axis_func><fit_points>[[392.3304241709184, 285.8125595021593], [388.7662174772938, 277.45998107106425], [393.66377872763235, 269.81256127078905], [397.2279854212569, 278.1651397018832]]</fit_points><axis>(8.027729719194863, 4.245549594342852)</axis><angle>-85.2</angle></bndbox></object><object><name>ellipse</name><bndbox><center>(589.0, 255.0)</center><points>[[598.2222222222222, 255.55555555555554], [589.7777777777778, 248.0], [578.6666666666666, 253.77777777777777], [587.5555555555555, 261.3333333333333]]</points><axis_func>(0.11504551725274716, -8.692211774441262, 186.9634875852336, 5371.473068495469)</axis_func><fit_points>[[578.9095868808538, 253.56444045051558], [587.8908954993644, 261.4009045490766], [598.4171129533088, 255.80869387784264], [589.4358043347981, 247.9722297792814]]</fit_points><axis>(9.818098681944225, 6.758625033664685)</axis><angle>6.6</angle></bndbox></object><object><name>ellipse</name><bndbox><center>(319.0, 361.0)</center><points>[[322.22222222222223, 354.22222222222223], [312.44444444444446, 358.22222222222223], [316.0, 368.44444444444446], [324.44444444444446, 364.0]]</points><axis_func>(-2.192662127953669, 0.45606660991319203, 1061.0395024491354, 215.89526903987579)</axis_func><fit_points>[[315.8546266783898, 368.47702459248546], [313.0165337277428, 358.6516584238658], [322.29621249730604, 354.3528033233845], [325.13430544795307, 364.17816949200403]]</fit_points><axis>(7.761888531810218, 6.659255139454086)</axis><angle>-65.5</angle></bndbox></object><object><name>ellipse</name><bndbox><center>(867.0, 312.0)</center><points>[[875.1111111111111, 323.1111111111111], [869.3333333333334, 310.22222222222223], [861.7777777777778, 305.77777777777777], [864.4444444444445, 314.22222222222223]]</points><axis_func>(1.2938883789012, -0.7728641776588498, -809.2358139726209, 982.2138693737751)</axis_func><fit_points>[[860.1080701745323, 303.6480226253441], [864.2954620678926, 314.23086782839766], [873.4808664015288, 320.9509282568688], [869.2934745081685, 310.3680830538151]]</fit_points><axis>(10.934146311237786, 3.15837120078932)</axis><angle>52.3</angle></bndbox></object><object><name>ellipse</name><bndbox><center>(923.0, 668.0)</center><points>[[932.4444444444445, 664.4444444444445], [916.8888888888889, 658.2222222222222], [846.2222222222222, 696.8888888888889], [929.7777777777778, 677.3333333333334]]</points><axis_func>(-0.38589927284420095, 2.591349773315888, 1024.187005660935, -1724.9585412586723)</axis_func><fit_points>[[880.4110140097093, 684.4370355505625], [919.2350010424301, 657.1008703166588], [966.3579356455584, 651.2701809880909], [927.5339486128377, 678.6063462219952]]</fit_points><axis>(46.06222307989196, 11.525602204346656)</axis><angle>-21.1</angle></bndbox></object><object><name>ellipse</name><bndbox><center>(639.0, 719.0)</center><points>[[653.3333333333334, 715.1111111111111], [635.5555555555555, 709.7777777777778], [629.3333333333334, 722.2222222222222], [643.1111111111111, 728.4444444444445]]</points><axis_func>(-0.33738316948303004, 2.9639889847178504, 934.961765542478, -1175.8922647596771)</axis_func><fit_points>[[627.52795699578, 723.2443944720312], [636.1680586034099, 709.7028533701698], [651.2457962850597, 715.2423946793249], [642.6056946774297, 728.7839357811868]]</fit_points><axis>(12.515669191403306, 10.068898452630373)</axis><angle>-18.6</angle></bndbox></object><object><name>ellipse</name><bndbox><center>(256.0, 490.0)</center><points>[[261.77777777777777, 484.44444444444446], [253.33333333333334, 487.1111111111111], [251.55555555555554, 495.1111111111111], [260.44444444444446, 494.22222222222223]]</points><axis_func>(-1.0293454689585622, 0.9714911369955818, 753.981058841879, 241.0857518517613)</axis_func><fit_points>[[251.19309289688633, 495.4165868347818], [252.7338317207477, 486.6144293874005], [261.48775816694354, 484.8198197846034], [259.9470193430822, 493.6219772319847]]</fit_points><axis>(7.387008950486504, 5.028314888437684)</axis><angle>-45.8</angle></bndbox></object></annotation>