<?xml version='1.0' encoding='utf-8'?>
<annotation><folder>polygonData</folder><filename>train105.png</filename><size><width>1024</width><height>768</height><depth>3</depth></size><object><name>circle</name><bndbox><points>[[61.3, 264.3], [65.7, 275.8]]</points><center>[61.3, 264.3]</center><R>12.313001258832067</R></bndbox></object><object><name>circle</name><bndbox><points>[[19.4, 337.3], [26.0, 347.5]]</points><center>[19.4, 337.3]</center><R>12.149074038789944</R></bndbox></object><object><name>circle</name><bndbox><points>[[128.6, 410.4], [135.3, 419.0]]</points><center>[128.6, 410.4]</center><R>10.901834707974645</R></bndbox></object><object><name>circle</name><bndbox><points>[[495.5, 394.3], [499.2, 400.4]]</points><center>[495.5, 394.3]</center><R>7.134423592694752</R></bndbox></object><object><name>circle</name><bndbox><points>[[471.9041278295606, 609.1664447403463], [478.8282290279627, 616.2237017310254]]</points><center>[471.9041278295606, 609.1664447403463]</center><R>9.886761534405625</R></bndbox></object><object><name>circle</name><bndbox><points>[[428.62849533954727, 614.4926764314248], [432.2237017310253, 619.5525965379494]]</points><center>[428.62849533954727, 614.4926764314248]</center><R>6.207116921867704</R></bndbox></object><object><name>circle</name><bndbox><points>[[322.4, 529.8], [326.3, 533.5]]</points><center>[322.4, 529.8]</center><R>5.375872022286301</R></bndbox></object><object><name>circle</name><bndbox><points>[[873.2, 476.8], [876.1, 482.1]]</points><center>[873.2, 476.8]</center><R>6.041522986797285</R></bndbox></object><object><name>circle</name><bndbox><points>[[864.0, 400.2], [867.2, 403.5]]</points><center>[864.0, 400.2]</center><R>4.5967379738245215</R></bndbox></object><object><name>circle</name><bndbox><points>[[886.6, 545.2], [889.0, 551.0]]</points><center>[886.6, 545.2]</center><R>6.276941930590036</R></bndbox></object><object><name>circle</name><bndbox><points>[[925.6, 590.0], [927.4, 593.6]]</points><center>[925.6, 590.0]</center><R>4.024922359499621</R></bndbox></object><object><name>circle</name><bndbox><points>[[1007.8, 213.5], [1013.5, 221.9]]</points><center>[1007.8, 213.5]</center><R>10.15135458941321</R></bndbox></object><object><name>circle</name><bndbox><points>[[404.2, 689.4], [407.1, 692.4]]</points><center>[404.2, 689.4]</center><R>4.172529209005036</R></bndbox></object><object><name>circle</name><bndbox><points>[[282.7, 671.8], [284.4, 676.2]]</points><center>[282.7, 671.8]</center><R>4.716990566028382</R></bndbox></object><object><name>ellipse</name><bndbox><center>(725.0, 386.0)</center><points>[[712.9, 385.5], [724.3, 380.1], [732.8, 385.5], [724.7, 390.5]]</points><axis_func>(-0.038461539431436556, 25.99999935013642, 413.3656811760714, -18451.69952916884)</axis_func><fit_points>[[714.5650436204812, 385.8824095745361], [724.3076923027008, 380.3000000001921], [734.4503409949036, 385.1175904254639], [724.707692312684, 390.6999999998079]]</fit_points><axis>(9.949999999999989, 5.2038447325030655)</axis><angle>-2.2</angle></bndbox></object><object><name>ellipse</name><bndbox><center>(758.0, 362.0)</center><points>[[747.6, 353.7], [763.1, 355.0], [767.9, 370.8], [750.6, 371.0]]</points><axis_func>(0.8191506891314624, -1.220776608309241, -258.4658316554383, 1286.9026925308185)</axis_func><fit_points>[[747.2941158899731, 353.6806583597201], [751.1274206294091, 369.9439075667798], [767.8270613451951, 370.50023477926396], [763.9937566057591, 354.23698557220405]]</fit_points><axis>(13.271209439986986, 10.151970252123476)</axis><angle>39.3</angle></bndbox></object><object><name>ellipse</name><bndbox><center>(615.0, 212.0)</center><points>[[612.5, 201.8], [622.0, 209.8], [617.9, 221.8], [607.6, 214.0]]</points><axis_func>(3.702006442773412, -0.2701237870525353, -2065.674370674318, 377.96357699406263)</axis_func><fit_points>[[612.4946747978445, 201.7848615917078], [607.9553359868228, 213.74037927850557], [617.8969822125841, 221.7842384469168], [622.4363210236058, 209.8287207601186]]</fit_points><axis>(10.358088626768934, 7.499999999999988)</axis><angle>74.9</angle></bndbox></object><object><name>ellipse</name><bndbox><center>(813.0, 496.0)</center><points>[[799.8, 491.1], [815.2, 487.2], [823.9, 499.3], [810.9, 504.7]]</points><axis_func>(0.30834547032055026, -3.2431155838300763, 244.91048608895295, 3132.7010739776733)</axis_func><fit_points>[[800.9641681814962, 491.88415923678474], [810.4725524934724, 504.2449087195532], [825.2907977929901, 499.38516528565464], [815.7824134810139, 487.0244158028863]]</fit_points><axis>(12.728413098261708, 9.010271915985674)</axis><angle>17.1</angle></bndbox></object><object><name>ellipse</name><bndbox><center>(846.0, 471.0)</center><points>[[839.6, 464.0], [852.2, 465.8], [852.8, 479.2], [839.9, 476.1]]</points><axis_func>(1.1661491323610458, -0.8575232726720694, -515.1896890408178, 1196.4527355415926)</axis_func><fit_points>[[839.2576328531167, 463.50987133822923], [839.7207759035458, 476.3726276580546], [852.3624340365153, 478.79202386801364], [851.8992909860862, 465.92926754818836]]</fit_points><axis>(10.065783625729269, 8.0215335192219)</axis><angle>49.4</angle></bndbox></object><object><name>ellipse</name><bndbox><center>(803.0, 583.0)</center><points>[[804.6, 577.0], [797.6, 582.6], [800.4, 589.9], [808.4, 584.3]]</points><axis_func>(-3.883623268757997, 0.2574915048912435, 3700.0774706319967, 376.7319240455715)</axis_func><fit_points>[[800.8329191417839, 589.9441114655733], [797.2305649191492, 582.0120219518994], [804.2158313703013, 576.806154818737], [807.8181855929361, 584.7382443324104]]</fit_points><axis>(6.7832514327570035, 5.466488818245191)</axis><angle>-75.6</angle></bndbox></object><object><name>ellipse</name><bndbox><center>(575.0, 624.0)</center><points>[[566.3, 615.1], [568.5, 629.6], [582.5, 633.0], [581.0, 618.5]]</points><axis_func>(1.1132145797024695, -0.8982994114595502, -15.381745276647402, 1140.3455881421798)</axis_func><fit_points>[[566.4892222701397, 615.242316198785], [568.3378500194516, 629.8080319595203], [582.6226790109266, 633.2023154636281], [580.7740512616148, 618.6365997028927]]</fit_points><axis>(12.071143276425815, 8.358528578643499)</axis><angle>48.1</angle></bndbox></object><object><name>ellipse</name><bndbox><center>(50.0, 592.0)</center><points>[[49.1, 600.2], [53.2, 591.9], [50.7, 584.1], [45.9, 591.2]]</points><axis_func>(-10.062533179051544, 0.09937856582907292, 1094.270407484757, 586.6243767072149)</axis_func><fit_points>[[49.15576325257162, 599.6389088141525], [46.30699175103042, 591.226299135291], [50.75575802850719, 583.5389082949916], [53.60452953004839, 591.9515179738532]]</fit_points><axis>(8.089653886292057, 3.66674242345982)</axis><angle>-84.3</angle></bndbox></object><object><name>ellipse</name><bndbox><center>(89.0, 594.0)</center><points>[[84.3, 591.6], [90.2, 591.5], [91.7, 596.0], [87.1, 596.3]]</points><axis_func>(0.6098723673843526, -1.6396866250427886, 540.1233435410284, 739.2460138482901)</axis_func><fit_points>[[84.84121146744201, 591.8656540304337], [87.02872681379912, 596.5461744972009], [92.1914166855278, 596.3483410875485], [90.00390133917068, 591.6678206207812]]</fit_points><axis>(4.304648650006174, 2.857008925432314)</axis><angle>31.4</angle></bndbox></object><object><name>ellipse</name><bndbox><center>(106.0, 601.0)</center><points>[[103.2, 592.5], [108.9, 599.7], [109.3, 608.9], [103.2, 602.2]]</points><axis_func>(2.6362813402925194, -0.37932214209644843, 320.59781873654293, 641.1621822807864)</axis_func><fit_points>[[103.19899072198885, 592.659392313943], [103.39212518094861, 601.9432598812448], [109.40479848062319, 609.0196475094732], [109.21166402166342, 599.7357799421713]]</fit_points><axis>(8.748857068211812, 3.1120732639190885)</axis><angle>69.2</angle></bndbox></object><object><name>circle</name><bndbox><points>[[225.9, 127.5], [228.9, 131.0]]</points><center>[225.9, 127.5]</center><R>4.6097722286464435</R></bndbox></object></annotation>