<?xml version='1.0' encoding='utf-8'?>
<annotation><folder>RectData</folder><filename>train19.png</filename><size><width>1024</width><height>768</height><depth>3</depth></size><object><name>circle</name><bndbox><xmin>271.0403512582127</xmin><ymin>376.81286310655395</ymin><xmax>289.9264733863371</xmax><ymax>395.69898523467833</ymax></bndbox></object><object><name>circle</name><bndbox><xmin>393.49529693105563</xmin><ymin>342.3634024466432</ymin><xmax>403.14738892026327</xmax><ymax>352.0154944358508</ymax></bndbox></object><object><name>circle</name><bndbox><xmin>373.2462297809588</xmin><ymin>118.73616266686487</ymin><xmax>383.23699169555124</xmax><ymax>128.72692458145733</ymax></bndbox></object><object><name>circle</name><bndbox><xmin>507.3674653731384</xmin><ymin>152.70175518662475</ymin><xmax>521.6138832638774</xmax><ymax>166.9481730773638</ymax></bndbox></object><object><name>circle</name><bndbox><xmin>634.7369614714613</xmin><ymin>76.46342683558207</ymin><xmax>653.3625056688585</xmax><ymax>95.08897103297925</ymax></bndbox></object><object><name>circle</name><bndbox><xmin>852.2671762177184</xmin><ymin>133.0088243246227</ymin><xmax>858.1470776798316</xmax><ymax>138.8887257867359</ymax></bndbox></object><object><name>circle</name><bndbox><xmin>937.956965239165</xmin><ymin>217.44214044132133</ymin><xmax>947.7573204751208</xmax><ymax>227.24249567727696</ymax></bndbox></object><object><name>circle</name><bndbox><xmin>971.8803753155306</xmin><ymin>237.75369067941202</ymin><xmax>984.4538564903993</xmax><ymax>250.32717185428064</ymax></bndbox></object><object><name>circle</name><bndbox><xmin>916.8634463588181</xmin><ymin>475.709273798705</ymin><xmax>933.7277841928084</xmax><ymax>492.57361163269525</ymax></bndbox></object><object><name>circle</name><bndbox><xmin>873.1312423843179</xmin><ymin>482.7550047605556</ymin><xmax>883.824910373815</xmax><ymax>493.44867275005254</ymax></bndbox></object><object><name>circle</name><bndbox><xmin>705.9894345711588</xmin><ymin>540.5670377145773</ymin><xmax>730.9457324229473</xmax><ymax>565.5233355663659</ymax></bndbox></object><object><name>circle</name><bndbox><xmin>584.4369303650113</xmin><ymin>677.4587644261468</ymin><xmax>595.4582661415387</xmax><ymax>688.4801002026742</ymax></bndbox></object><object><name>circle</name><bndbox><xmin>728.9084113575913</xmin><ymin>25.361963270159592</ymin><xmax>750.2828454730098</xmax><ymax>46.736397385578144</ymax></bndbox></object><object><name>ellipse</name><bndbox><xmin>154.8240740740741</xmin><ymin>652.0555555555555</ymin><xmax>167.55555555555557</xmax><ymax>671.7314814814815</ymax></bndbox></object><object><name>ellipse</name><bndbox><xmin>262.78740157480314</xmin><ymin>328.93700787401576</ymin><xmax>284.8346456692913</xmax><ymax>339.1732283464567</ymax></bndbox></object><object><name>ellipse</name><bndbox><xmin>283.8503937007874</xmin><ymin>302.3622047244094</ymin><xmax>292.70866141732284</xmax><ymax>314.1732283464567</ymax></bndbox></object><object><name>ellipse</name><bndbox><xmin>256.359102244389</xmin><ymin>153.82543640897754</ymin><xmax>274.3142144638404</xmax><ymax>181.00748129675807</ymax></bndbox></object></annotation>