<?xml version='1.0' encoding='utf-8'?>
<annotation><folder>RectData</folder><filename>train110.png</filename><size><width>1024</width><height>768</height><depth>3</depth></size><object><name>circle</name><bndbox><xmin>557.3150282309657</xmin><ymin>479.7150282309657</ymin><xmax>565.2849717690342</xmax><ymax>487.6849717690343</ymax></bndbox></object><object><name>circle</name><bndbox><xmin>876.0216538638466</xmin><ymin>91.66913587823515</ymin><xmax>886.2085619634914</xmax><ymax>101.85604397787995</ymax></bndbox></object><object><name>circle</name><bndbox><xmin>678.4948751620467</xmin><ymin>177.19487516204666</ymin><xmax>686.3051248379533</xmax><ymax>185.00512483795333</ymax></bndbox></object><object><name>circle</name><bndbox><xmin>928.5344553097673</xmin><ymin>178.1344553097673</ymin><xmax>935.4655446902327</xmax><ymax>185.06554469023268</ymax></bndbox></object><object><name>ellipse</name><bndbox><xmin>899.0815154994259</xmin><ymin>594.4890929965557</ymin><xmax>920.2066590126291</xmax><ymax>618.2548794489093</ymax></bndbox></object><object><name>ellipse</name><bndbox><xmin>970.1492537313432</xmin><ymin>636.2801377726751</ymin><xmax>977.6119402985074</xmax><ymax>653.6165327210102</ymax></bndbox></object><object><name>ellipse</name><bndbox><xmin>1002.4110218140067</xmin><ymin>639.7244546498277</ymin><xmax>1013.5476463834672</xmax><ymax>654.6498277841561</ymax></bndbox></object><object><name>ellipse</name><bndbox><xmin>725.7</xmin><ymin>532.6</ymin><xmax>739.4</xmax><ymax>543.4</ymax></bndbox></object><object><name>ellipse</name><bndbox><xmin>348.2</xmin><ymin>574.6</ymin><xmax>374.4</xmax><ymax>590.4</ymax></bndbox></object><object><name>ellipse</name><bndbox><xmin>349.7</xmin><ymin>625.2</ymin><xmax>359.9</xmax><ymax>639.7</ymax></bndbox></object><object><name>ellipse</name><bndbox><xmin>292.8</xmin><ymin>507.8</ymin><xmax>308.2</xmax><ymax>521.5</ymax></bndbox></object><object><name>ellipse</name><bndbox><xmin>255.0</xmin><ymin>384.9</ymin><xmax>266.1</xmax><ymax>402.1</ymax></bndbox></object><object><name>ellipse</name><bndbox><xmin>234.6</xmin><ymin>418.7</ymin><xmax>247.0</xmax><ymax>433.4</ymax></bndbox></object><object><name>ellipse</name><bndbox><xmin>636.4</xmin><ymin>396.0</ymin><xmax>643.9</xmax><ymax>405.0</ymax></bndbox></object><object><name>ellipse</name><bndbox><xmin>578.6</xmin><ymin>301.9</ymin><xmax>599.6</xmax><ymax>326.4</ymax></bndbox></object><object><name>ellipse</name><bndbox><xmin>374.0</xmin><ymin>138.9</ymin><xmax>396.4</xmax><ymax>164.6</ymax></bndbox></object><object><name>ellipse</name><bndbox><xmin>208.3</xmin><ymin>36.1</ymin><xmax>226.4</xmax><ymax>61.1</ymax></bndbox></object><object><name>ellipse</name><bndbox><xmin>719.7</xmin><ymin>277.3</ymin><xmax>728.2</xmax><ymax>284.7</ymax></bndbox></object><object><name>ellipse</name><bndbox><xmin>826.7032967032967</xmin><ymin>53.61538461538458</ymin><xmax>850.8791208791209</xmax><ymax>73.28571428571425</ymax></bndbox></object><object><name>ellipse</name><bndbox><xmin>788.2417582417582</xmin><ymin>85.59340659340656</ymin><xmax>804.2857142857143</xmax><ymax>96.032967032967</ymax></bndbox></object><object><name>ellipse</name><bndbox><xmin>771.3186813186813</xmin><ymin>86.032967032967</ymin><xmax>780.2197802197802</xmax><ymax>98.45054945054942</ymax></bndbox></object><object><name>ellipse</name><bndbox><xmin>857.2</xmin><ymin>325.1</ymin><xmax>880.0</xmax><ymax>337.3</ymax></bndbox></object><object><name>ellipse</name><bndbox><xmin>1009.2</xmin><ymin>228.6</ymin><xmax>1018.6</xmax><ymax>236.3</ymax></bndbox></object></annotation>